spire/__init__.py
spire/common/Bitmap.py
spire/common/Boolean.py
spire/common/Byte.py
spire/common/Char.py
spire/common/Color.py
spire/common/Common.py
spire/common/CultureInfo.py
spire/common/DateTime.py
spire/common/Double.py
spire/common/EmfType.py
spire/common/Encoding.py
spire/common/Font.py
spire/common/FontStyle.py
spire/common/GraphicsUnit.py
spire/common/ICollection.py
spire/common/IDictionary.py
spire/common/IEnumerable.py
spire/common/IEnumerator.py
spire/common/IList.py
spire/common/Image.py
spire/common/ImageFormat.py
spire/common/Int16.py
spire/common/Int32.py
spire/common/Int64.py
spire/common/License.py
spire/common/PixelFormat.py
spire/common/Point.py
spire/common/PointF.py
spire/common/Rectangle.py
spire/common/RectangleF.py
spire/common/Single.py
spire/common/Size.py
spire/common/SizeF.py
spire/common/SpireObject.py
spire/common/Stream.py
spire/common/String.py
spire/common/TimeSpan.py
spire/common/UInt16.py
spire/common/UInt32.py
spire/common/UInt64.py
spire/common/__init__.py
spire/lib/Spire.Xls.Base.dll
spire/lib/__init__.py
spire/lib/libSkiaSharp.dll
spire/xls/AddInFunctionsCollection.py
spire/xls/AddtionalFormatWrapper.py
spire/xls/AlertStyleType.py
spire/xls/ArcShapeCollection.py
spire/xls/AutoFiltersCollection.py
spire/xls/AutoFitterOptions.py
spire/xls/AutoFormatOptions.py
spire/xls/AutoFormatType.py
spire/xls/AutoSortScope.py
spire/xls/Average.py
spire/xls/AverageType.py
spire/xls/AxisLineIdentifierType.py
spire/xls/AxisTextDirectionType.py
spire/xls/AxisType.py
spire/xls/AxisTypes.py
spire/xls/BaseFormatType.py
spire/xls/BordersCollection.py
spire/xls/BordersCollectionArrayWrapper.py
spire/xls/BordersLineType.py
spire/xls/BubbleSizeType.py
spire/xls/BuiltInDocumentProperties.py
spire/xls/BuiltInPropertyType.py
spire/xls/BuiltInStyles.py
spire/xls/ButtonShapeCollection.py
spire/xls/CategoryType.py
spire/xls/CellBaseStyle.py
spire/xls/CellBorder.py
spire/xls/CellDataType.py
spire/xls/CellFormatType.py
spire/xls/CellRange.py
Spire.XLS_for_Python-13.5.0.dist-info/METADATA
Spire.XLS_for_Python-13.5.0.dist-info/WHEEL
Spire.XLS_for_Python-13.5.0.dist-info/top_level.txt
Spire.XLS_for_Python-13.5.0.dist-info/RECORD
