Metadata-Version: 2.1
Name: Spire.XLS-for-Python
Version: 13.5.0
Summary: A 100% standalone Excel Python API for Processing Excel Files
Home-page: https://www.e-iceblue.com
Author: e-iceblue
Author-email: sales@e-iceblue.com
License: UNKNOWN
Platform: UNKNOWN
Classifier: Programming Language :: Python :: 3.6
Classifier: License :: Free To Use But Restricted
Classifier: License :: Other/Proprietary License
Classifier: Operating System :: Microsoft :: Windows
Classifier: Operating System :: POSIX :: Linux
Classifier: Operating System :: Unix
Requires-Python: >=3.9
Requires-Dist: plum-dispatch
